RIPPLE CARRY ADDER/rca_4bit.v
module full_adder(
    input a,
    input b,
    input cin,
    output sum,
    output cout
);

assign sum  = a ^ b ^ cin;
assign cout = (a & b) | (b & cin) | (a & cin);

endmodule

module rca_4bit (
        input wire [3:0] a,
        input wire [3:0] b,
        input wire cin,
        output wire [3:0] sum,
        output wire cout
);

//internal wirs
wire c1, c2, c3;

//instantiating 4 full adders, because 4 bit ripple carry adderhas 4 full adders, summing each bit it requires a adder

full_adder FA0 (
        .a (a[0]),
        .b (b[0]),
        .cin (cin),
        .sum (sum[0]),
        .cout (c1)
);

full_adder FA1 (
        .a (a[1]),
        .b (b[1]),
        .cin (c1),
        .sum (sum[1]),
        .cout (c2)
);

full_adder FA2 (
        .a (a[2]),
        .b (b[2]),
        .cin (c2),
        .sum (sum[2]),
        .cout (c3)
);

full_adder FA3 (
        .a (a[3]),
        .b (b[3]),
        .cin (c3),
        .sum (sum[3]),
        .cout (cout)
);

endmodule

RIPPLE CARRY ADDER/tb_rca_4bit.v
//  Testbench — 4-bit Ripple Carry Adder
//
//  Strategy:
//    - Exhaustive: all 256 combinations of A and B (4-bit each)
//    - tested with cin=0 AND cin=1 → 512 total test vectors



`timescale 1ns/1ps

module tb_rca_4bit;

    // Inputs 
    reg  [3:0] a;
    reg  [3:0] b;
    reg        cin;

    // Outputs
    wire [3:0] sum;
    wire       cout;

    // DUT instantiation
    rca_4bit DUT (
        .a   (a),
        .b   (b),
        .cin (cin),
        .sum (sum),
        .cout(cout)
    );

    // Waveform dump 
    initial begin
        $dumpfile("rca_4bit.vcd");
        $dumpvars(0, tb_rca_4bit);
    end

    // Test variables 
    integer i, j;
    integer pass_count, fail_count;
    reg [4:0] expected;   // bit[4]=cout, bits[3]=sum

    // Main stimulus 
    initial begin
        pass_count = 0;
        fail_count = 0;

        $display("-------------------------------------------");
        $display("  4-bit Ripple Carry Adder, exhaustive TB ");
        $display("  Testing all 256x2 that is 512 input vectors");
        $display("--------------------------------------------");

        // Sweep all A, B combinations for both cin values
        for (i = 0; i < 16; i = i + 1) begin
            for (j = 0; j < 16; j = j + 1) begin

                // Test with cin = 0
                a   = i[3:0];
                b   = j[3:0];
                cin = 0;
                #20;  // delay

                expected = a + b + cin;  

                if ({cout, sum} === expected) begin
                    pass_count = pass_count + 1;
                end else begin
                    $display("  FAIL: %0d + %0d + cin=%b | got cout=%b sum=%0d | expected cout=%b sum=%0d",
                             a, b, cin, cout, sum, expected[4], expected[3:0]);
                    fail_count = fail_count + 1;
                end

                // Test with cin = 1 
                cin = 1;
                #20;

                expected = a + b + cin;

                if ({cout, sum} === expected) begin
                    pass_count = pass_count + 1;
                end else begin
                    $display("  FAIL: %0d + %0d + cin=%b | got cout=%b sum=%0d | expected cout=%b sum=%0d",
                             a, b, cin, cout, sum, expected[4], expected[3:0]);
                    fail_count = fail_count + 1;
                end

            end
        end

        $display("----------------------------------------------");
        $display("  Results: %0d PASSED, %0d FAILED", pass_count, fail_count);
        if (fail_count == 0)
            $display("  *** ALL 512 TESTS PASSED ***");
        else
            $display("  *** FAILURES DETECTED recheck ***");
        $display("------------------------------------------------");

        // ── Interesting corner cases: print these explicitly ──
        $display("");
        $display("  Corner case spot-check:");
        $display("  ----------------------");

        a = 4'b1111; b = 4'b0001; cin = 0; #20;  // 15 + 1 = 16 → sum=0, cout=1
        $display("  15 + 1  = sum=%0d, cout=%b  (expect sum=0, cout=1)", sum, cout);

        a = 4'b1111; b = 4'b1111; cin = 0; #20;  // 15 + 15 = 30 → sum=14, cout=1
        $display("  15 + 15 = sum=%0d, cout=%b  (expect sum=14, cout=1)", sum, cout);

        a = 4'b0111; b = 4'b0001; cin = 0; #20;  // 7 + 1 = 8 → no overflow
        $display("  7  + 1  = sum=%0d, cout=%b  (expect sum=8, cout=0)", sum, cout);

        a = 4'b0000; b = 4'b0000; cin = 0; #20;  // 0 + 0 = 0
        $display("  0  + 0  = sum=%0d, cout=%b  (expect sum=0, cout=0)", sum, cout);

        $finish;
    end

endmodule

RIPPLE CARRY ADDER/rca_4bit.vcd
$date
	Tue Jun 30 23:11:39 2026
$end
$version
	Icarus Verilog
$end
$timescale
	1ps
$end
$scope module tb_rca_4bit $end
$var wire 4 ! sum [3:0] $end
$var wire 1 " cout $end
$var reg 4 # a [3:0] $end
$var reg 4 $ b [3:0] $end
$var reg 1 % cin $end
$var reg 5 & expected [4:0] $end
$var integer 32 ' fail_count [31:0] $end
$var integer 32 ( i [31:0] $end
$var integer 32 ) j [31:0] $end
$var integer 32 * pass_count [31:0] $end
$scope module DUT $end
$var wire 4 + a [3:0] $end
$var wire 4 , b [3:0] $end
$var wire 1 % cin $end
$var wire 4 - sum [3:0] $end
$var wire 1 " cout $end
$var wire 1 . c3 $end
$var wire 1 / c2 $end
$var wire 1 0 c1 $end
$scope module FA0 $end
$var wire 1 1 a $end
$var wire 1 2 b $end
$var wire 1 % cin $end
$var wire 1 0 cout $end
$var wire 1 3 sum $end
$upscope $end
$scope module FA1 $end
$var wire 1 4 a $end
$var wire 1 5 b $end
$var wire 1 0 cin $end
$var wire 1 / cout $end
$var wire 1 6 sum $end
$upscope $end
$scope module FA2 $end
$var wire 1 7 a $end
$var wire 1 8 b $end
$var wire 1 / cin $end
$var wire 1 . cout $end
$var wire 1 9 sum $end
$upscope $end
$scope module FA3 $end
$var wire 1 : a $end
$var wire 1 ; b $end
$var wire 1 . cin $end
$var wire 1 " cout $end
$var wire 1 < sum $end
$upscope $end
$upscope $end
$upscope $end
$enddefinitions $end
$comment Show the parameter values. $end
$dumpall
$end
#0
$dumpvars
0<
0;
0:
09
08
07
06
05
04
03
02
01
00
0/
0.
b0 -
b0 ,
b0 +
b0 *
b0 )
b0 (
b0 '
bx &
0%
b0 $
b0 #
0"
b0 !
$end
#20000
b1 !
b1 -
13
1%
b1 *
b0 &
#40000
b1 !
b1 -
13
12
0%
b1 $
b1 ,
b1 )
b10 *
b1 &
#60000
16
10
b10 !
b10 -
03
1%
b11 *
#80000
09
0/
00
16
b10 !
b10 -
03
02
15
0%
b10 $
b10 ,
b10 )
b100 *
b10 &
#100000
b11 !
b11 -
13
1%
b101 *
#120000
b11 !
b11 -
13
12
0%
b11 $
b11 ,
b11 )
b110 *
b11 &
#140000
19
1/
06
10
b100 !
b100 -
03
1%
b111 *
#160000
0<
0/
0.
00
06
19
b100 !
b100 -
03
02
05
18
0%
b100 $
b100 ,
b100 )
b1000 *
b100 &
#180000
b101 !
b101 -
13
1%
b1001 *
#200000
b101 !
b101 -
13
12
0%
b101 $
b101 ,
b101 )
b1010 *
b101 &
#220000
16
10
b110 !
b110 -
03
1%
b1011 *
#240000
0<
0.
19
0/
00
16
b110 !
b110 -
03
02
15
0%
b110 $
b110 ,
b110 )
b1100 *
b110 &
#260000
b111 !
b111 -
13
1%
b1101 *
#280000
b111 !
b111 -
13
12
0%
b111 $
b111 ,
b111 )
b1110 *
b111 &
#300000
1<
1.
09
1/
06
10
b1000 !
b1000 -
03
1%
b1111 *
#320000
0/
0.
0"
00
06
09
1<
b1000 !
b1000 -
03
02
05
08
1;
0%
b1000 $
b1000 ,
b1000 )
b10000 *
b1000 &
#340000
b1001 !
b1001 -
13
1%
b10001 *
#360000
b1001 !
b1001 -
13
12
0%
b1001 $
b1001 ,
b1001 )
b10010 *
b1001 &
#380000
16
10
b1010 !
b1010 -
03
1%
b10011 *
#400000
09
0/
00
16
b1010 !
b1010 -
03
02
15
0%
b1010 $
b1010 ,
b1010 )
b10100 *
b1010 &
#420000
b1011 !
b1011 -
13
1%
b10101 *
#440000
b1011 !
b1011 -
13
12
0%
b1011 $
b1011 ,
b1011 )
b10110 *
b1011 &
#460000
19
1/
06
10
b1100 !
b1100 -
03
1%
b10111 *
#480000
0"
1<
0/
0.
00
06
19
b1100 !
b1100 -
03
02
05
18
0%
b1100 $
b1100 ,
b1100 )
b11000 *
b1100 &
#500000
b1101 !
b1101 -
13
1%
b11001 *
#520000
b1101 !
b1101 -
13
12
0%
b1101 $
b1101 ,
b1101 )
b11010 *
b1101 &
#540000
16
10
b1110 !
b1110 -
03
1%
b11011 *
#560000
0"
1<
0.
19
0/
00
16
b1110 !
b1110 -
03
02
15
0%
b1110 $
b1110 ,
b1110 )
b11100 *
b1110 &
#580000
b1111 !
b1111 -
13
1%
b11101 *
#600000
b1111 !
b1111 -
13
12
0%
b1111 $
b1111 ,
b1111 )
b11110 *
b1111 &
#620000
1"
0<
1.
09
1/
06
10
b0 !
b0 -
03
1%
b11111 *
#640000
0/
0.
0"
00
06
09
0<
b1 !
b1 -
13
02
05
08
0;
11
0%
b0 $
b0 ,
b1 #
b1 +
b1 (
b0 )
b100000 *
b10000 &
#660000
16
10
b10 !
b10 -
03
1%
b100001 *
b1 &
#680000
16
10
b10 !
b10 -
03
12
0%
b1 $
b1 ,
b1 )
b100010 *
b10 &
#700000
b11 !
b11 -
13
1%
b100011 *
#720000
09
0/
00
16
b11 !
b11 -
13
02
15
0%
b10 $
b10 ,
b10 )
b100100 *
b11 &
#740000
19
1/
06
10
b100 !
b100 -
03
1%
b100101 *
#760000
19
1/
06
10
b100 !
b100 -
03
12
0%
b11 $
b11 ,
b11 )
b100110 *
b100 &
#780000
b101 !
b101 -
13
1%
b100111 *
#800000
0<
0/
0.
00
06
19
b101 !
b101 -
13
02
05
18
0%
b100 $
b100 ,
b100 )
b101000 *
b101 &
#820000
16
10
b110 !
b110 -
03
1%
b101001 *
#840000
16
10
b110 !
b110 -
03
12
0%
b101 $
b101 ,
b101 )
b101010 *
b110 &
#860000
b111 !
b111 -
13
1%
b101011 *
#880000
0<
0.
19
0/
00
16
b111 !
b111 -
13
02
15
0%
b110 $
b110 ,
b110 )
b101100 *
b111 &
#900000
1<
1.
09
1/
06
10
b1000 !
b1000 -
03
1%
b101101 *
#920000
1<
1.
09
1/
06
10
b1000 !
b1000 -
03
12
0%
b111 $
b111 ,
b111 )
b101110 *
b1000 &
#940000
b1001 !
b1001 -
13
1%
b101111 *
#960000
0/
0.
0"
00
06
09
1<
b1001 !
b1001 -
13
02
05
08
1;
0%
b1000 $
b1000 ,
b1000 )
b110000 *
b1001 &
#980000
16
10
b1010 !
b1010 -
03
1%
b110001 *
#1000000
16
10
b1010 !
b1010 -
03
12
0%
b1001 $
b1001 ,
b1001 )
b110010 *
b1010 &
#1020000
b1011 !
b1011 -
13
1%
b110011 *
#1040000
09
0/
00
16
b1011 !
b1011 -
13
02
15
0%
b1010 $
b1010 ,
b1010 )
b110100 *
b1011 &
#1060000
19
1/
06
10
b1100 !
b1100 -
03
1%
b110101 *
#1080000
19
1/
06
10
b1100 !
b1100 -
03
12
0%
b1011 $
b1011 ,
b1011 )
b110110 *
b1100 &
#1100000
b1101 !
b1101 -
13
1%
b110111 *
#1120000
0"
1<
0/
0.
00
06
19
b1101 !
b1101 -
13
02
05
18
0%
b1100 $
b1100 ,
b1100 )
b111000 *
b1101 &
#1140000
16
10
b1110 !
b1110 -
03
1%
b111001 *
#1160000
16
10
b1110 !
b1110 -
03
12
0%
b1101 $
b1101 ,
b1101 )
b111010 *
b1110 &
#1180000
b1111 !
b1111 -
13
1%
b111011 *
#1200000
0"
1<
0.
19
0/
00
16
b1111 !
b1111 -
13
02
15
0%
b1110 $
b1110 ,
b1110 )
b111100 *
b1111 &
#1220000
1"
0<
1.
09
1/
06
10
b0 !
b0 -
03
1%
b111101 *
#1240000
1"
0<
1.
09
1/
06
10
b0 !
b0 -
03
12
0%
b1111 $
b1111 ,
b1111 )
b111110 *
b10000 &
#1260000
b1 !
b1 -
13
1%
b111111 *
#1280000
0/
16
0.
0"
00
09
0<
b10 !
b10 -
03
02
05
08
0;
01
14
0%
b0 $
b0 ,
b10 #
b10 +
b10 (
b0 )
b1000000 *
b10001 &
#1300000
b11 !
b11 -
13
1%
b1000001 *
b10 &
#1320000
b11 !
b11 -
13
12
0%
b1 $
b1 ,
b1 )
b1000010 *
b11 &
#1340000
19
1/
06
10
b100 !
b100 -
03
1%
b1000011 *
#1360000
00
06
b100 !
b100 -
03
02
15
0%
b10 $
b10 ,
b10 )
b1000100 *
b100 &
#1380000
b101 !
b101 -
13
1%
b1000101 *
#1400000
b101 !
b101 -
13
12
0%
b11 $
b11 ,
b11 )
b1000110 *
b101 &
#1420000
16
10
b110 !
b110 -
03
1%
b1000111 *
#1440000
0/
0<
0.
00
16
19
b110 !
b110 -
03
02
05
18
0%
b100 $
b100 ,
b100 )
b1001000 *
b110 &
#1460000
b111 !
b111 -
13
1%
b1001001 *
#1480000
b111 !
b111 -
13
12
0%
b101 $
b101 ,
b101 )
b1001010 *
b111 &
#1500000
1<
1.
09
1/
06
10
b1000 !
b1000 -
03
1%
b1001011 *
#1520000
00
06
b1000 !
b1000 -
03
02
15
0%
b110 $
b110 ,
b110 )
b1001100 *
b1000 &
#1540000
b1001 !
b1001 -
13
1%
b1001101 *
#1560000
b1001 !
b1001 -
13
12
0%
b111 $
b111 ,
b111 )
b1001110 *
b1001 &
#1580000
16
10
b1010 !
b1010 -
03
1%
b1001111 *
#1600000
0/
0.
0"
00
16
09
1<
b1010 !
b1010 -
03
02
05
08
1;
0%
b1000 $
b1000 ,
b1000 )
b1010000 *
b1010 &
#1620000
b1011 !
b1011 -
13
1%
b1010001 *
#1640000
b1011 !
b1011 -
13
12
0%
b1001 $
b1001 ,
b1001 )
b1010010 *
b1011 &
#1660000
19
1/
06
10
b1100 !
b1100 -
03
1%
b1010011 *
#1680000
00
06
b1100 !
b1100 -
03
02
15
0%
b1010 $
b1010 ,
b1010 )
b1010100 *
b1100 &
#1700000
b1101 !
b1101 -
13
1%
b1010101 *
#1720000
b1101 !
b1101 -
13
12
0%
b1011 $
b1011 ,
b1011 )
b1010110 *
b1101 &
#1740000
16
10
b1110 !
b1110 -
03
1%
b1010111 *
#1760000
0"
0/
1<
0.
00
16
19
b1110 !
b1110 -
03
02
05
18
0%
b1100 $
b1100 ,
b1100 )
b1011000 *
b1110 &
#1780000
b1111 !
b1111 -
13
1%
b1011001 *
#1800000
b1111 !
b1111 -
13
12
0%
b1101 $
b1101 ,
b1101 )
b1011010 *
b1111 &
#1820000
1"
0<
1.
09
1/
06
10
b0 !
b0 -
03
1%
b1011011 *
#1840000
00
06
b0 !
b0 -
03
02
15
0%
b1110 $
b1110 ,
b1110 )
b1011100 *
b10000 &
#1860000
b1 !
b1 -
13
1%
b1011101 *
#1880000
b1 !
b1 -
13
12
0%
b1111 $
b1111 ,
b1111 )
b1011110 *
b10001 &
#1900000
16
10
b10 !
b10 -
03
1%
b1011111 *
#1920000
0/
0.
0"
00
16
09
0<
b11 !
b11 -
13
02
05
08
0;
11
0%
b0 $
b0 ,
b11 #
b11 +
b11 (
b0 )
b1100000 *
b10010 &
#1940000
19
1/
06
10
b100 !
b100 -
03
1%
b1100001 *
b11 &
#1960000
19
1/
06
10
b100 !
b100 -
03
12
0%
b1 $
b1 ,
b1 )
b1100010 *
b100 &
#1980000
b101 !
b101 -
13
1%
b1100011 *
#2000000
00
06
b101 !
b101 -
13
02
15
0%
b10 $
b10 ,
b10 )
b1100100 *
b101 &
#2020000
16
10
b110 !
b110 -
03
1%
b1100101 *
#2040000
16
10
b110 !
b110 -
03
12
0%
b11 $
b11 ,
b11 )
b1100110 *
b110 &
#2060000
b111 !
b111 -
13
1%
b1100111 *
#2080000
0/
0<
0.
00
16
19
b111 !
b111 -
13
02
05
18
0%
b100 $
b100 ,
b100 )
b1101000 *
b111 &
#2100000
1<
1.
09
1/
06
10
b1000 !
b1000 -
03
1%
b1101001 *
#2120000
1<
1.
09
1/
06
10
b1000 !
b1000 -
03
12
0%
b101 $
b101 ,
b101 )
b1101010 *
b1000 &
#2140000
b1001 !
b1001 -
13
1%
b1101011 *
#2160000
00
06
b1001 !
b1001 -
13
02
15
0%
b110 $
b110 ,
b110 )
b1101100 *
b1001 &
#2180000
16
10
b1010 !
b1010 -
03
1%
b1101101 *
#2200000
16
10
b1010 !
b1010 -
03
12
0%
b111 $
b111 ,
b111 )
b1101110 *
b1010 &
#2220000
b1011 !
b1011 -
13
1%
b1101111 *
#2240000
0/
0.
0"
00
16
09
1<
b1011 !
b1011 -
13
02
05
08
1;
0%
b1000 $
b1000 ,
b1000 )
b1110000 *
b1011 &
#2260000
19
1/
06
10
b1100 !
b1100 -
03
1%
b1110001 *
#2280000
19
1/
06
10
b1100 !
b1100 -
03
12
0%
b1001 $
b1001 ,
b1001 )
b1110010 *
b1100 &
#2300000
b1101 !
b1101 -
13
1%
b1110011 *
#2320000
00
06
b1101 !
b1101 -
13
02
15
0%
b1010 $
b1010 ,
b1010 )
b1110100 *
b1101 &
#2340000
16
10
b1110 !
b1110 -
03
1%
b1110101 *
#2360000
16
10
b1110 !
b1110 -
03
12
0%
b1011 $
b1011 ,
b1011 )
b1110110 *
b1110 &
#2380000
b1111 !
b1111 -
13
1%
b1110111 *
#2400000
0"
0/
1<
0.
00
16
19
b1111 !
b1111 -
13
02
05
18
0%
b1100 $
b1100 ,
b1100 )
b1111000 *
b1111 &
#2420000
1"
0<
1.
09
1/
06
10
b0 !
b0 -
03
1%
b1111001 *
#2440000
1"
0<
1.
09
1/
06
10
b0 !
b0 -
03
12
0%
b1101 $
b1101 ,
b1101 )
b1111010 *
b10000 &
#2460000
b1 !
b1 -
13
1%
b1111011 *
#2480000
00
06
b1 !
b1 -
13
02
15
0%
b1110 $
b1110 ,
b1110 )
b1111100 *
b10001 &
#2500000
16
10
b10 !
b10 -
03
1%
b1111101 *
#2520000
16
10
b10 !
b10 -
03
12
0%
b1111 $
b1111 ,
b1111 )
b1111110 *
b10010 &
#2540000
b11 !
b11 -
13
1%
b1111111 *
#2560000
0.
19
06
0"
0/
00
0<
b100 !
b100 -
03
02
05
08
0;
01
04
17
0%
b0 $
b0 ,
b100 #
b100 +
b100 (
b0 )
b10000000 *
b10011 &
#2580000
b101 !
b101 -
13
1%
b10000001 *
b100 &
#2600000
b101 !
b101 -
13
12
0%
b1 $
b1 ,
b1 )
b10000010 *
b101 &
#2620000
16
10
b110 !
b110 -
03
1%
b10000011 *
#2640000
0<
0.
19
0/
00
16
b110 !
b110 -
03
02
15
0%
b10 $
b10 ,
b10 )
b10000100 *
b110 &
#2660000
b111 !
b111 -
13
1%
b10000101 *
#2680000
b111 !
b111 -
13
12
0%
b11 $
b11 ,
b11 )
b10000110 *
b111 &
#2700000
1<
1.
09
1/
06
10
b1000 !
b1000 -
03
1%
b10000111 *
#2720000
0/
00
06
09
b1000 !
b1000 -
03
02
05
18
0%
b100 $
b100 ,
b100 )
b10001000 *
b1000 &
#2740000
b1001 !
b1001 -
13
1%
b10001001 *
#2760000
b1001 !
b1001 -
13
12
0%
b101 $
b101 ,
b101 )
b10001010 *
b1001 &
#2780000
16
10
b1010 !
b1010 -
03
1%
b10001011 *
#2800000
09
0/
00
16
b1010 !
b1010 -
03
02
15
0%
b110 $
b110 ,
b110 )
b10001100 *
b1010 &
#2820000
b1011 !
b1011 -
13
1%
b10001101 *
#2840000
b1011 !
b1011 -
13
12
0%
b111 $
b111 ,
b111 )
b10001110 *
b1011 &
#2860000
19
1/
06
10
b1100 !
b1100 -
03
1%
b10001111 *
#2880000
0.
0/
0"
00
06
19
1<
b1100 !
b1100 -
03
02
05
08
1;
0%
b1000 $
b1000 ,
b1000 )
b10010000 *
b1100 &
#2900000
b1101 !
b1101 -
13
1%
b10010001 *
#2920000
b1101 !
b1101 -
13
12
0%
b1001 $
b1001 ,
b1001 )
b10010010 *
b1101 &
#2940000
16
10
b1110 !
b1110 -
03
1%
b10010011 *
#2960000
0"
1<
0.
19
0/
00
16
b1110 !
b1110 -
03
02
15
0%
b1010 $
b1010 ,
b1010 )
b10010100 *
b1110 &
#2980000
b1111 !
b1111 -
13
1%
b10010101 *
#3000000
b1111 !
b1111 -
13
12
0%
b1011 $
b1011 ,
b1011 )
b10010110 *
b1111 &
#3020000
1"
0<
1.
09
1/
06
10
b0 !
b0 -
03
1%
b10010111 *
#3040000
0/
00
06
09
b0 !
b0 -
03
02
05
18
0%
b1100 $
b1100 ,
b1100 )
b10011000 *
b10000 &
#3060000
b1 !
b1 -
13
1%
b10011001 *
#3080000
b1 !
b1 -
13
12
0%
b1101 $
b1101 ,
b1101 )
b10011010 *
b10001 &
#3100000
16
10
b10 !
b10 -
03
1%
b10011011 *
#3120000
09
0/
00
16
b10 !
b10 -
03
02
15
0%
b1110 $
b1110 ,
b1110 )
b10011100 *
b10010 &
#3140000
b11 !
b11 -
13
1%
b10011101 *
#3160000
b11 !
b11 -
13
12
0%
b1111 $
b1111 ,
b1111 )
b10011110 *
b10011 &
#3180000
19
1/
06
10
b100 !
b100 -
03
1%
b10011111 *
#3200000
0.
0/
0"
00
06
19
0<
b101 !
b101 -
13
02
05
08
0;
11
0%
b0 $
b0 ,
b101 #
b101 +
b101 (
b0 )
b10100000 *
b10100 &
#3220000
16
10
b110 !
b110 -
03
1%
b10100001 *
b101 &
#3240000
16
10
b110 !
b110 -
03
12
0%
b1 $
b1 ,
b1 )
b10100010 *
b110 &
#3260000
b111 !
b111 -
13
1%
b10100011 *
#3280000
0<
0.
19
0/
00
16
b111 !
b111 -
13
02
15
0%
b10 $
b10 ,
b10 )
b10100100 *
b111 &
#3300000
1<
1.
09
1/
06
10
b1000 !
b1000 -
03
1%
b10100101 *
#3320000
1<
1.
09
1/
06
10
b1000 !
b1000 -
03
12
0%
b11 $
b11 ,
b11 )
b10100110 *
b1000 &
#3340000
b1001 !
b1001 -
13
1%
b10100111 *
#3360000
0/
00
06
09
b1001 !
b1001 -
13
02
05
18
0%
b100 $
b100 ,
b100 )
b10101000 *
b1001 &
#3380000
16
10
b1010 !
b1010 -
03
1%
b10101001 *
#3400000
16
10
b1010 !
b1010 -
03
12
0%
b101 $
b101 ,
b101 )
b10101010 *
b1010 &
#3420000
b1011 !
b1011 -
13
1%
b10101011 *
#3440000
09
0/
00
16
b1011 !
b1011 -
13
02
15
0%
b110 $
b110 ,
b110 )
b10101100 *
b1011 &
#3460000
19
1/
06
10
b1100 !
b1100 -
03
1%
b10101101 *
#3480000
19
1/
06
10
b1100 !
b1100 -
03
12
0%
b111 $
b111 ,
b111 )
b10101110 *
b1100 &
#3500000
b1101 !
b1101 -
13
1%
b10101111 *
#3520000
0.
0/
0"
00
06
19
1<
b1101 !
b1101 -
13
02
05
08
1;
0%
b1000 $
b1000 ,
b1000 )
b10110000 *
b1101 &
#3540000
16
10
b1110 !
b1110 -
03
1%
b10110001 *
#3560000
16
10
b1110 !
b1110 -
03
12
0%
b1001 $
b1001 ,
b1001 )
b10110010 *
b1110 &
#3580000
b1111 !
b1111 -
13
1%
b10110011 *
#3600000
0"
1<
0.
19
0/
00
16
b1111 !
b1111 -
13
02
15
0%
b1010 $
b1010 ,
b1010 )
b10110100 *
b1111 &
#3620000
1"
0<
1.
09
1/
06
10
b0 !
b0 -
03
1%
b10110101 *
#3640000
1"
0<
1.
09
1/
06
10
b0 !
b0 -
03
12
0%
b1011 $
b1011 ,
b1011 )
b10110110 *
b10000 &
#3660000
b1 !
b1 -
13
1%
b10110111 *
#3680000
0/
00
06
09
b1 !
b1 -
13
02
05
18
0%
b1100 $
b1100 ,
b1100 )
b10111000 *
b10001 &
#3700000
16
10
b10 !
b10 -
03
1%
b10111001 *
#3720000
16
10
b10 !
b10 -
03
12
0%
b1101 $
b1101 ,
b1101 )
b10111010 *
b10010 &
#3740000
b11 !
b11 -
13
1%
b10111011 *
#3760000
09
0/
00
16
b11 !
b11 -
13
02
15
0%
b1110 $
b1110 ,
b1110 )
b10111100 *
b10011 &
#3780000
19
1/
06
10
b100 !
b100 -
03
1%
b10111101 *
#3800000
19
1/
06
10
b100 !
b100 -
03
12
0%
b1111 $
b1111 ,
b1111 )
b10111110 *
b10100 &
#3820000
b101 !
b101 -
13
1%
b10111111 *
#3840000
0.
0/
16
0"
00
19
0<
b110 !
b110 -
03
02
05
08
0;
01
14
0%
b0 $
b0 ,
b110 #
b110 +
b110 (
b0 )
b11000000 *
b10101 &
#3860000
b111 !
b111 -
13
1%
b11000001 *
b110 &
#3880000
b111 !
b111 -
13
12
0%
b1 $
b1 ,
b1 )
b11000010 *
b111 &
#3900000
1<
1.
09
1/
06
10
b1000 !
b1000 -
03
1%
b11000011 *
#3920000
00
06
b1000 !
b1000 -
03
02
15
0%
b10 $
b10 ,
b10 )
b11000100 *
b1000 &
#3940000
b1001 !
b1001 -
13
1%
b11000101 *
#3960000
b1001 !
b1001 -
13
12
0%
b11 $
b11 ,
b11 )
b11000110 *
b1001 &
#3980000
16
10
b1010 !
b1010 -
03
1%
b11000111 *
#4000000
0/
00
16
09
b1010 !
b1010 -
03
02
05
18
0%
b100 $
b100 ,
b100 )
b11001000 *
b1010 &
#4020000
b1011 !
b1011 -
13
1%
b11001001 *
#4040000
b1011 !
b1011 -
13
12
0%
b101 $
b101 ,
b101 )
b11001010 *
b1011 &
#4060000
19
1/
06
10
b1100 !
b1100 -
03
1%
b11001011 *
#4080000
00
06
b1100 !
b1100 -
03
02
15
0%
b110 $
b110 ,
b110 )
b11001100 *
b1100 &
#4100000
b1101 !
b1101 -
13
1%
b11001101 *
#4120000
b1101 !
b1101 -
13
12
0%
b111 $
b111 ,
b111 )
b11001110 *
b1101 &
#4140000
16
10
b1110 !
b1110 -
03
1%
b11001111 *
#4160000
0.
0/
0"
00
16
19
1<
b1110 !
b1110 -
03
02
05
08
1;
0%
b1000 $
b1000 ,
b1000 )
b11010000 *
b1110 &
#4180000
b1111 !
b1111 -
13
1%
b11010001 *
#4200000
b1111 !
b1111 -
13
12
0%
b1001 $
b1001 ,
b1001 )
b11010010 *
b1111 &
#4220000
1"
0<
1.
09
1/
06
10
b0 !
b0 -
03
1%
b11010011 *
#4240000
00
06
b0 !
b0 -
03
02
15
0%
b1010 $
b1010 ,
b1010 )
b11010100 *
b10000 &
#4260000
b1 !
b1 -
13
1%
b11010101 *
#4280000
b1 !
b1 -
13
12
0%
b1011 $
b1011 ,
b1011 )
b11010110 *
b10001 &
#4300000
16
10
b10 !
b10 -
03
1%
b11010111 *
#4320000
0/
00
16
09
b10 !
b10 -
03
02
05
18
0%
b1100 $
b1100 ,
b1100 )
b11011000 *
b10010 &
#4340000
b11 !
b11 -
13
1%
b11011001 *
#4360000
b11 !
b11 -
13
12
0%
b1101 $
b1101 ,
b1101 )
b11011010 *
b10011 &
#4380000
19
1/
06
10
b100 !
b100 -
03
1%
b11011011 *
#4400000
00
06
b100 !
b100 -
03
02
15
0%
b1110 $
b1110 ,
b1110 )
b11011100 *
b10100 &
#4420000
b101 !
b101 -
13
1%
b11011101 *
#4440000
b101 !
b101 -
13
12
0%
b1111 $
b1111 ,
b1111 )
b11011110 *
b10101 &
#4460000
16
10
b110 !
b110 -
03
1%
b11011111 *
#4480000
0.
0/
0"
00
16
19
0<
b111 !
b111 -
13
02
05
08
0;
11
0%
b0 $
b0 ,
b111 #
b111 +
b111 (
b0 )
b11100000 *
b10110 &
#4500000
1<
1.
09
1/
06
10
b1000 !
b1000 -
03
1%
b11100001 *
b111 &
#4520000
1<
1.
09
1/
06
10
b1000 !
b1000 -
03
12
0%
b1 $
b1 ,
b1 )
b11100010 *
b1000 &
#4540000
b1001 !
b1001 -
13
1%
b11100011 *
#4560000
00
06
b1001 !
b1001 -
13
02
15
0%
b10 $
b10 ,
b10 )
b11100100 *
b1001 &
#4580000
16
10
b1010 !
b1010 -
03
1%
b11100101 *
#4600000
16
10
b1010 !
b1010 -
03
12
0%
b11 $
b11 ,
b11 )
b11100110 *
b1010 &
#4620000
b1011 !
b1011 -
13
1%
b11100111 *
#4640000
0/
00
16
09
b1011 !
b1011 -
13
02
05
18
0%
b100 $
b100 ,
b100 )
b11101000 *
b1011 &
#4660000
19
1/
06
10
b1100 !
b1100 -
03
1%
b11101001 *
#4680000
19
1/
06
10
b1100 !
b1100 -
03
12
0%
b101 $
b101 ,
b101 )
b11101010 *
b1100 &
#4700000
b1101 !
b1101 -
13
1%
b11101011 *
#4720000
00
06
b1101 !
b1101 -
13
02
15
0%
b110 $
b110 ,
b110 )
b11101100 *
b1101 &
#4740000
16
10
b1110 !
b1110 -
03
1%
b11101101 *
#4760000
16
10
b1110 !
b1110 -
03
12
0%
b111 $
b111 ,
b111 )
b11101110 *
b1110 &
#4780000
b1111 !
b1111 -
13
1%
b11101111 *
#4800000
0.
0/
0"
00
16
19
1<
b1111 !
b1111 -
13
02
05
08
1;
0%
b1000 $
b1000 ,
b1000 )
b11110000 *
b1111 &
#4820000
1"
0<
1.
09
1/
06
10
b0 !
b0 -
03
1%
b11110001 *
#4840000
1"
0<
1.
09
1/
06
10
b0 !
b0 -
03
12
0%
b1001 $
b1001 ,
b1001 )
b11110010 *
b10000 &
#4860000
b1 !
b1 -
13
1%
b11110011 *
#4880000
00
06
b1 !
b1 -
13
02
15
0%
b1010 $
b1010 ,
b1010 )
b11110100 *
b10001 &
#4900000
16
10
b10 !
b10 -
03
1%
b11110101 *
#4920000
16
10
b10 !
b10 -
03
12
0%
b1011 $
b1011 ,
b1011 )
b11110110 *
b10010 &
#4940000
b11 !
b11 -
13
1%
b11110111 *
#4960000
0/
00
16
09
b11 !
b11 -
13
02
05
18
0%
b1100 $
b1100 ,
b1100 )
b11111000 *
b10011 &
#4980000
19
1/
06
10
b100 !
b100 -
03
1%
b11111001 *
#5000000
19
1/
06
10
b100 !
b100 -
03
12
0%
b1101 $
b1101 ,
b1101 )
b11111010 *
b10100 &
#5020000
b101 !
b101 -
13
1%
b11111011 *
#5040000
00
06
b101 !
b101 -
13
02
15
0%
b1110 $
b1110 ,
b1110 )
b11111100 *
b10101 &
