ALU_8bit/8bit_alu.v
`timescale 1ns/1ps

module alu #(
    parameter WIDTH = 8
)(
    input  wire [WIDTH-1:0] a,
    input  wire [WIDTH-1:0] b,
    input  wire [2:0]       op,
    output reg  [WIDTH-1:0] result,
    output wire             zero,
    output reg              carry,
    output reg              overflow,
    output wire             negative
);
    reg [WIDTH:0] full_result;

    always @(*) begin
        full_result = {(WIDTH+1){1'b0}};
        overflow    = 1'b0;
        carry       = 1'b0;

        case (op)

            3'b000: begin  // ADD
                full_result = {1'b0, a} + {1'b0, b};
                carry       = full_result[WIDTH];
                overflow    = (a[WIDTH-1] == b[WIDTH-1]) &&
                              (full_result[WIDTH-1] != a[WIDTH-1]);
            end

            3'b001: begin  // SUB
                full_result = {1'b0, a} - {1'b0, b};
                carry       = full_result[WIDTH];
                overflow    = (a[WIDTH-1] != b[WIDTH-1]) &&
                              (full_result[WIDTH-1] != a[WIDTH-1]);
            end

            3'b010: begin  // AND
                full_result = {1'b0, a & b};
            end

            3'b011: begin  // OR
                full_result = {1'b0, a | b};
            end

            3'b100: begin  // XOR
                full_result = {1'b0, a ^ b};
            end

            3'b101: begin  // NOT
                full_result = {1'b0, ~a};
            end

            3'b110: begin  // SHL
                full_result = {a, 1'b0};
                carry       = a[WIDTH-1];
            end

            3'b111: begin  // SHR
                full_result = {1'b0, a[WIDTH-1:0]} >> 1;
                carry       = a[0];
            end

        endcase

        result = full_result[WIDTH-1:0];
    end

    assign zero     = (result == {WIDTH{1'b0}});
    assign negative = result[WIDTH-1];

endmodule

ALU_8bit/8bit_alu_tb.v
`timescale 1ns/1ps

module tb_alu;

    localparam ADD = 3'b000;
    localparam SUB = 3'b001;
    localparam AND = 3'b010;
    localparam OR  = 3'b011;
    localparam XOR = 3'b100;
    localparam NOT = 3'b101;
    localparam SHL = 3'b110;
    localparam SHR = 3'b111;

    reg  [7:0] a, b;
    reg  [2:0] op;
    wire [7:0] result;
    wire       zero, carry, overflow, negative;

    alu #(.WIDTH(8)) DUT (
        .a        (a),
        .b        (b),
        .op       (op),
        .result   (result),
        .zero     (zero),
        .carry    (carry),
        .overflow (overflow),
        .negative (negative)
    );

    initial begin
        $dumpfile("8bit_alu.vcd");
        $dumpvars(0, tb_alu);
    end

    integer pass_count, fail_count;

    task check_result;
        input [7:0]  exp_result;
        input        exp_zero;
        input        exp_carry;
        input        exp_overflow;
        input        exp_negative;
        input [63:0] test_name;
        begin
            if (result   === exp_result   &&
                zero     === exp_zero     &&
                carry    === exp_carry    &&
                overflow === exp_overflow &&
                negative === exp_negative) begin
                pass_count = pass_count + 1;
            end else begin
                $display("  FAIL [%s] a=%0d b=%0d op=%b",
                         test_name, a, b, op);
                $display("       result:   got=%0d  exp=%0d",   result,   exp_result);
                $display("       zero:     got=%b    exp=%b",   zero,     exp_zero);
                $display("       carry:    got=%b    exp=%b",   carry,    exp_carry);
                $display("       overflow: got=%b    exp=%b",   overflow, exp_overflow);
                $display("       negative: got=%b    exp=%b",   negative, exp_negative);
                fail_count = fail_count + 1;
            end
        end
    endtask

    initial begin
        pass_count = 0;
        fail_count = 0;

        $display("================================================");
        $display("  8-bit ALU Testbench — Directed Corner Cases   ");
        $display("================================================");

        // ADD
        $display("\n  [ADD]");
        op = ADD;
        a=8'd1;   b=8'd1;   #10; check_result(8'd2,   0,0,0,0, "ADD 1+1 ");
        a=8'd0;   b=8'd0;   #10; check_result(8'd0,   1,0,0,0, "ADD 0+0 ");
        a=8'd255; b=8'd1;   #10; check_result(8'd0,   1,1,0,0, "ADD OvfU");
        a=8'd127; b=8'd1;   #10; check_result(8'd128, 0,0,1,1, "ADD OvfS");
        a=8'd200; b=8'd100; #10; check_result(8'd44,  0,1,0,0, "ADD crry");

        // SUB
        $display("\n  [SUB]");
        op = SUB;
        a=8'd5;   b=8'd3;   #10; check_result(8'd2,   0,0,0,0, "SUB 5-3 ");
        a=8'd7;   b=8'd7;   #10; check_result(8'd0,   1,0,0,0, "SUB 7-7 ");
        a=8'd0;   b=8'd1;   #10; check_result(8'd255, 0,1,0,1, "SUB brw ");
        a=8'h80;  b=8'd1;   #10; check_result(8'h7F, 0,0,1,0,  "SUB OvfS");

        // AND
        $display("\n  [AND]");
        op = AND;
        a=8'hFF; b=8'hAA; #10; check_result(8'hAA, 0,0,0,1, "AND FFA ");
        a=8'hFF; b=8'h00; #10; check_result(8'h00, 1,0,0,0, "AND FF0 ");
        a=8'hF0; b=8'h0F; #10; check_result(8'h00, 1,0,0,0, "AND mask");

        // OR
        $display("\n  [OR]");
        op = OR;
        a=8'hF0; b=8'h0F; #10; check_result(8'hFF, 0,0,0,1, "OR F00F ");
        a=8'h00; b=8'h00; #10; check_result(8'h00, 1,0,0,0, "OR  0+0 ");
        a=8'hAA; b=8'h55; #10; check_result(8'hFF, 0,0,0,1, "OR AA55 ");

        // XOR
        $display("\n  [XOR]");
        op = XOR;
        a=8'hFF; b=8'hFF; #10; check_result(8'h00, 1,0,0,0, "XOR same");
        a=8'hAA; b=8'h55; #10; check_result(8'hFF, 0,0,0,1, "XOR AA55");
        a=8'hF0; b=8'h0F; #10; check_result(8'hFF, 0,0,0,1, "XOR F00F");

        // NOT
        $display("\n  [NOT]");
        op = NOT;
        a=8'h00; b=8'h00; #10; check_result(8'hFF, 0,0,0,1, "NOT 00  ");
        a=8'hFF; b=8'h00; #10; check_result(8'h00, 1,0,0,0, "NOT FF  ");
        a=8'hAA; b=8'h00; #10; check_result(8'h55, 0,0,0,0, "NOT AA  ");

        // SHL
        $display("\n  [SHL]");
        op = SHL;
        a=8'b00000001; b=8'h00; #10; check_result(8'b00000010, 0,0,0,0, "SHL 01  ");
        a=8'b10000000; b=8'h00; #10; check_result(8'b00000000, 1,1,0,0, "SHL MSB ");
        a=8'b01010101; b=8'h00; #10; check_result(8'b10101010, 0,0,0,1, "SHL 55  ");

        // SHR
        $display("\n  [SHR]");
        op = SHR;
        a=8'b10000000; b=8'h00; #10; check_result(8'b01000000, 0,0,0,0, "SHR 80  ");
        a=8'b00000001; b=8'h00; #10; check_result(8'b00000000, 1,1,0,0, "SHR LSB ");
        a=8'b10101010; b=8'h00; #10; check_result(8'b01010101, 0,0,0,0, "SHR AA  ");

        $display("\n================================================");
        $display("  Results: %0d PASSED, %0d FAILED", pass_count, fail_count);
        if (fail_count == 0)
            $display("  *** ALL TESTS PASSED ***");
        else
            $display("  *** FAILURES DETECTED — check above ***");
        $display("================================================");

        $finish;
    end

endmodule

ALU_8bit/8bit_alu.vcd
$date
	Sat Aug 22 11:43:50 2026
$end
$version
	Icarus Verilog
$end
$timescale
	1ps
$end
$scope module tb_alu $end
$var wire 1 ! zero $end
$var wire 8 " result [7:0] $end
$var wire 1 # overflow $end
$var wire 1 $ negative $end
$var wire 1 % carry $end
$var parameter 3 & ADD $end
$var parameter 3 ' AND $end
$var parameter 3 ( NOT $end
$var parameter 3 ) OR $end
$var parameter 3 * SHL $end
$var parameter 3 + SHR $end
$var parameter 3 , SUB $end
$var parameter 3 - XOR $end
$var reg 8 . a [7:0] $end
$var reg 8 / b [7:0] $end
$var reg 3 0 op [2:0] $end
$var integer 32 1 fail_count [31:0] $end
$var integer 32 2 pass_count [31:0] $end
$scope module DUT $end
$var wire 8 3 a [7:0] $end
$var wire 8 4 b [7:0] $end
$var wire 3 5 op [2:0] $end
$var wire 1 ! zero $end
$var wire 1 $ negative $end
$var parameter 32 6 WIDTH $end
$var reg 1 % carry $end
$var reg 9 7 full_result [8:0] $end
$var reg 1 # overflow $end
$var reg 8 8 result [7:0] $end
$upscope $end
$scope task check_result $end
$var reg 1 9 exp_carry $end
$var reg 1 : exp_negative $end
$var reg 1 ; exp_overflow $end
$var reg 8 < exp_result [7:0] $end
$var reg 1 = exp_zero $end
$var reg 64 > test_name [63:0] $end
$upscope $end
$upscope $end
$enddefinitions $end
$comment Show the parameter values. $end
$dumpall
b1000 6
b100 -
b1 ,
b111 +
b110 *
b11 )
b101 (
b10 '
b0 &
$end
#0
$dumpvars
bx >
x=
bx <
x;
x:
x9
b10 8
b10 7
b0 5
b1 4
b1 3
b0 2
b0 1
b0 0
b1 /
b1 .
0%
0$
0#
b10 "
0!
$end
#10000
1!
b0 "
b0 8
b0 7
b0 /
b0 4
b0 .
b0 3
b1 2
b100000101000100010001000010000000110001001010110011000100100000 >
0:
0;
09
0=
b10 <
#20000
1%
b100000000 7
b1 /
b1 4
b11111111 .
b11111111 3
b10 2
b100000101000100010001000010000000110000001010110011000000100000 >
1=
b0 <
#30000
1$
0!
b10000000 "
b10000000 8
1#
0%
b10000000 7
b1111111 .
b1111111 3
b11 2
b100000101000100010001000010000001001111011101100110011001010101 >
19
#40000
0$
b101100 "
b101100 8
1%
0#
b100101100 7
b1100100 /
b1100100 4
b11001000 .
b11001000 3
b100 2
b100000101000100010001000010000001001111011101100110011001010011 >
1:
1;
09
0=
b10000000 <
#50000
b10 "
b10 8
0%
b10 7
b11 /
b11 4
b101 .
b101 3
b1 0
b1 5
b101 2
b100000101000100010001000010000001100011011100100111001001111001 >
0:
0;
19
b101100 <
#60000
1!
b0 "
b0 8
b0 7
b111 /
b111 4
b111 .
b111 3
b110 2
b101001101010101010000100010000000110101001011010011001100100000 >
09
b10 <
#70000
1$
0!
b11111111 "
b11111111 8
1%
b111111111 7
b1 /
b1 4
b0 .
b0 3
b111 2
b101001101010101010000100010000000110111001011010011011100100000 >
1=
b0 <
#80000
0$
b1111111 "
b1111111 8
1#
0%
b1111111 7
b10000000 .
b10000000 3
b1000 2
b101001101010101010000100010000001100010011100100111011100100000 >
1:
19
0=
b11111111 <
#90000
1$
b10101010 "
b10101010 8
0#
b10101010 7
b10101010 /
b10101010 4
b11111111 .
b11111111 3
b10 0
b10 5
b1001 2
b101001101010101010000100010000001001111011101100110011001010011 >
0:
1;
09
b1111111 <
#100000
0$
1!
b0 "
b0 8
b0 7
b0 /
b0 4
b1010 2
b100000101001110010001000010000001000110010001100100000100100000 >
1:
0;
b10101010 <
#110000
b1111 /
b1111 4
b11110000 .
b11110000 3
b1011 2
b100000101001110010001000010000001000110010001100011000000100000 >
0:
1=
b0 <
#120000
1$
0!
b11111111 "
b11111111 8
b11111111 7
b11 0
b11 5
b1100 2
b100000101001110010001000010000001101101011000010111001101101011 >
#130000
0$
1!
b0 "
b0 8
b0 7
b0 /
b0 4
b0 .
b0 3
b1101 2
b100111101010010001000000100011000110000001100000100011000100000 >
1:
0=
b11111111 <
#140000
1$
0!
b11111111 "
b11111111 8
b11111111 7
b1010101 /
b1010101 4
b10101010 .
b10101010 3
b1110 2
b100111101010010001000000010000000110000001010110011000000100000 >
0:
1=
b0 <
#150000
0$
1!
b0 "
b0 8
b0 7
b11111111 /
b11111111 4
b11111111 .
b11111111 3
b100 0
b100 5
b1111 2
b100111101010010001000000100000101000001001101010011010100100000 >
1:
0=
b11111111 <
#160000
1$
0!
b11111111 "
b11111111 8
b11111111 7
b1010101 /
b1010101 4
b10101010 .
b10101010 3
b10000 2
b101100001001111010100100010000001110011011000010110110101100101 >
0:
1=
b0 <
#170000
b11111111 7
b1111 /
b1111 4
b11110000 .
b11110000 3
b10001 2
b101100001001111010100100010000001000001010000010011010100110101 >
1:
0=
b11111111 <
#180000
b11111111 7
b0 /
b0 4
b0 .
b0 3
b101 0
b101 5
b10010 2
b101100001001111010100100010000001000110001100000011000001000110 >
#190000
0$
1!
b0 "
b0 8
b0 7
b11111111 .
b11111111 3
b10011 2
b100111001001111010101000010000000110000001100000010000000100000 >
#200000
0!
b1010101 "
b1010101 8
b1010101 7
b10101010 .
b10101010 3
b10100 2
b100111001001111010101000010000001000110010001100010000000100000 >
0:
1=
b0 <
#210000
b10 "
b10 8
b10 7
b1 .
b1 3
b110 0
b110 5
b10101 2
b100111001001111010101000010000001000001010000010010000000100000 >
0=
b1010101 <
#220000
1!
b0 "
b0 8
1%
b100000000 7
b10000000 .
b10000000 3
b10110 2
b101001101001000010011000010000000110000001100010010000000100000 >
b10 <
#230000
1$
0!
b10101010 "
b10101010 8
0%
b10101010 7
b1010101 .
b1010101 3
b10111 2
b101001101001000010011000010000001001101010100110100001000100000 >
19
1=
b0 <
#240000
0$
b1000000 "
b1000000 8
b1000000 7
b10000000 .
b10000000 3
b111 0
b111 5
b11000 2
b101001101001000010011000010000000110101001101010010000000100000 >
1:
09
0=
b10101010 <
#250000
1!
b0 "
b0 8
1%
b0 7
b1 .
b1 3
b11001 2
b101001101001000010100100010000000111000001100000010000000100000 >
0:
b1000000 <
#260000
0!
b1010101 "
b1010101 8
b1010101 7
0%
b10101010 .
b10101010 3
b11010 2
b101001101001000010100100010000001001100010100110100001000100000 >
19
1=
b0 <
#270000
b11011 2
b101001101001000010100100010000001000001010000010010000000100000 >
09
0=
b1010101 <
